LICENSE
MANIFEST.in
README.md
requirements.txt
setup.cfg
setup.py
hydro_opendata/__init__.py
hydro_opendata/common.py
hydro_opendata/utils.py
hydro_opendata.egg-info/PKG-INFO
hydro_opendata.egg-info/SOURCES.txt
hydro_opendata.egg-info/dependency_links.txt
hydro_opendata.egg-info/not-zip-safe
hydro_opendata.egg-info/requires.txt
hydro_opendata.egg-info/top_level.txt
hydro_opendata/catalog/__init__.py
hydro_opendata/catalog/minio.py
hydro_opendata/catalog/s3.py
hydro_opendata/data/minio.py
hydro_opendata/downloader/__init__.py
hydro_opendata/downloader/dem.py
hydro_opendata/downloader/downloader.py
hydro_opendata/downloader/hydrostation.py
hydro_opendata/downloader/ncep_gfs.py
hydro_opendata/reader/__init__.py
hydro_opendata/reader/era5.py
hydro_opendata/reader/gfs.py
hydro_opendata/reader/gpm.py
hydro_opendata/reader/grdc.py
hydro_opendata/reader/minio.py
hydro_opendata/reader/reader.py
tests/test.py
tests/test_aoi_reading.py
tests/test_downloader.py
tests/test_processor.py
tests/test_reader.py