Metadata-Version: 2.1
Name: hydro-opendata
Version: 0.0.8
Summary: A open-data solution for WIS
Home-page: https://github.com/zjf014/hydro-opendata
Author: Jeff Zhu
Author-email: zjf014@gmail.com
License: MIT license
Keywords: hydro_opendata
Classifier: Development Status :: 2 - Pre-Alpha
Classifier: Intended Audience :: Developers
Classifier: License :: OSI Approved :: MIT License
Classifier: Natural Language :: English
Classifier: Programming Language :: Python :: 3
Classifier: Programming Language :: Python :: 3.7
Classifier: Programming Language :: Python :: 3.8
Classifier: Programming Language :: Python :: 3.9
Classifier: Programming Language :: Python :: 3.10
Classifier: Programming Language :: Python :: 3.11
Requires-Python: >=3.7
License-File: LICENSE
Requires-Dist: minio
Requires-Dist: boto3<=1.28.64
Requires-Dist: s3fs>=2023.10
Requires-Dist: kerchunk
Requires-Dist: xarray
Requires-Dist: zarr
Requires-Dist: dask
Requires-Dist: cfgrib
Requires-Dist: eccodes
Requires-Dist: netCDF4
Requires-Dist: h5py
Requires-Dist: geopandas
Requires-Dist: openpyxl>=3.0.10
Requires-Dist: requests
Requires-Dist: tqdm
Requires-Dist: wget
Requires-Dist: hydrodataset
Requires-Dist: dataretrieval
Requires-Dist: pygeohydro
